yoloproc/__init__.py
yoloproc/archive_extractor.py
yoloproc/dataset_crop.py
yoloproc/label_info.py
yoloproc/label_rewrite.py
yoloproc/script.py
yoloproc/yolo2coco.py
yoloproc/yolo_im_visual.py
yoloproc/yolo_visual_cls.py
yoloproc-0.1.2.dist-info/LICENSE
yoloproc-0.1.2.dist-info/METADATA
yoloproc-0.1.2.dist-info/WHEEL
yoloproc-0.1.2.dist-info/RECORD
